Workbook
Name Aporte: 'SIMULADOR DE INVESTIMENTO'!$E$25:$E$25
Name Patrimonio: 'SIMULADOR DE INVESTIMENTO'!$E$28:$E$28
Name Perfis: 'SIMULADOR DE INVESTIMENTO'!$D$42:$D$42
Name Qtd_Anos: 'SIMULADOR DE INVESTIMENTO'!$E$26:$E$26
Name Rendimento_Carteira: 'SIMULADOR DE INVESTIMENTO'!$E$19:$E$19
Name Salario: 'SIMULADOR DE INVESTIMENTO'!$E$18:$E$18
Name Sugestao_Investimento: 'SIMULADOR DE INVESTIMENTO'!$E$20:$E$20
Name Taxa_Mensal: 'SIMULADOR DE INVESTIMENTO'!$E$27:$E$27

Sheet SIMULADOR DE INVESTIMENTO
C17: CONFIGURAÇÕES
C18: Salário | E18: 1000
C19: Rendimento da carteira | E19: 0.008
C20: Sugestão de investimento (30%) | E20: {=Salario*30%} -> 300
C24: INVESTIMENTO MENSAL
C25: Quanto investir por mês? | E25: 300
C26: Quantos anos? | E26: 2
C27: Taxa de rendimento mensal? | E27: 0.01079
C28: Total do patrimônio acumulado? | E28: {=FV(Taxa_Mensal,Qtd_Anos*12,Aporte*-1)} -> 8168.2882
C29: Quantos dividendos mensais? | E29: {=Patrimonio*Rendimento_Carteira} -> 65.346306
C33: CENÁRIOS | E33: DIVIDENDOS
B34: 2 | C34: Patrimonio acumulado em 2 anos? | D34: {=FV(Taxa_Mensal,$B34*12,Aporte*-1)} -> 8168.2882 | E34: {=D34*Rendimento_Carteira} -> 65.346306
B35: 5 | C35: Patrimonio acumulado em 5 anos? | D35: {=FV(Taxa_Mensal,$B35*12,Aporte*-1)} -> 25133.074 | E35: {=D35*Rendimento_Carteira} -> 201.06459
B36: 10 | C36: Patrimonio acumulado em 10 anos? | D36: {=FV(Taxa_Mensal,$B36*12,Aporte*-1)} -> 72985.264 | E36: {=D36*Rendimento_Carteira} -> 583.88211
B37: 20 | C37: Patrimonio acumulado em 20 anos? | D37: {=FV(Taxa_Mensal,$B37*12,Aporte*-1)} -> 337559.52 | E37: {=D37*Rendimento_Carteira} -> 2700.4762
B38: 50 | C38: Patrimonio acumulado em 50 anos? | D38: {=FV(Taxa_Mensal,$B38*12,Aporte*-1)} -> 17376707 | E38: {=D38*Rendimento_Carteira} -> 139013.66
C42: PERFIS | D42: Conservador
C43: VALOR INVESTIDO POR MÊS | D43: {=Aporte} -> 300
C46: TIPOS DE FII | D46: Percentual Sugerido | E46: Valores
C47: PAPEL | D47: =VLOOKUP($D$42&"-"&C47,Regras!A:D,4,FALSE) -> 0.3 | E47: {=D47*Aporte} -> 90
C48: TIJOLO | D48: =VLOOKUP($D$42&"-"&C48,Regras!A:D,4,FALSE) -> 0.5 | E48: {=D48*Aporte} -> 150
C49: HIBRÍDOS | D49: =VLOOKUP($D$42&"-"&C49,Regras!A:D,4,FALSE) -> 0.1 | E49: {=D49*Aporte} -> 30
C50: FOFs | D50: =VLOOKUP($D$42&"-"&C50,Regras!A:D,4,FALSE) -> 0.1 | E50: {=D50*Aporte} -> 30
C51: DESENVOLVIMENTO | D51: =VLOOKUP($D$42&"-"&C51,Regras!A:D,4,FALSE) -> 0 | E51: {=D51*Aporte} -> 0
C52: HOTELARIAS | D52: =VLOOKUP($D$42&"-"&C52,Regras!A:D,4,FALSE) -> 0 | E52: {=D52*Aporte} -> 0
E53: =SUM(E47:E52) -> 300

Sheet Regras
A2: CHAVES COMPOSTA | B2: Perfil | C2: TIPO DE FII | D2: %
A3: Conservador-PAPEL | B3: Conservador | C3: PAPEL | D3: 0.3
A4: Conservador-TIJOLO | B4: Conservador | C4: TIJOLO | D4: 0.5
A5: Conservador-HIBRÍDOS | B5: Conservador | C5: HIBRÍDOS | D5: 0.1 | H5: %
A6: Conservador-FOFs | B6: Conservador | C6: FOFs | D6: 0.1 | F6: TESTE PROCV | G6: Agressivo-HIBRÍDOS | H6: =VLOOKUP(G6,$A:$D,4,FALSE) -> 0.15
A7: Conservador-DESENVOLVIMENTO | B7: Conservador | C7: DESENVOLVIMENTO | D7: 0
A8: Conservador-HOTELARIAS | B8: Conservador | C8: HOTELARIAS | D8: 0
A9: Moderado-PAPEL | B9: Moderado | C9: PAPEL | D9: 0.3
A10: Moderado-TIJOLO | B10: Moderado | C10: TIJOLO | D10: 0.2
A11: Moderado-HIBRÍDOS | B11: Moderado | C11: HIBRÍDOS | D11: 0.2
A12: Moderado-FOFs | B12: Moderado | C12: FOFs | D12: 0.12
A13: Moderado-DESENVOLVIMENTO | B13: Moderado | C13: DESENVOLVIMENTO | D13: 0.08
A14: Moderado-HOTELARIAS | B14: Moderado | C14: HOTELARIAS | D14: 0.1
A15: Agressivo-PAPEL | B15: Agressivo | C15: PAPEL | D15: 0.5
A16: Agressivo-TIJOLO | B16: Agressivo | C16: TIJOLO | D16: 0.1
A17: Agressivo-HIBRÍDOS | B17: Agressivo | C17: HIBRÍDOS | D17: 0.15
A18: Agressivo-FOFs | B18: Agressivo | C18: FOFs | D18: 0.05
... A20: Agressivo-HOTELARIAS | B20: Agressivo | C20: HOTELARIAS | D20: 0.1
